shilver/__init__.py
shilver/_encoder.py
shilver/_solution.py
shilver/_solver.py
shilver/shilver_lp/__init__.py
shilver/shilver_lp/black_white_minimizer.lp
shilver/shilver_lp/solver.lp
shilver/shilver_lp/viz.lp
shilver-0.0.1.dist-info/METADATA
shilver-0.0.1.dist-info/WHEEL
shilver-0.0.1.dist-info/licenses/LICENSE
shilver-0.0.1.dist-info/RECORD
