Metadata-Version: 2.1
Name: shilver
Version: 0.0.1
Summary: An outstandingly fast Shingoki solver.
Project-URL: homepage, https://github.com/bramucas/shilver
Project-URL: repository, https://github.com/bramucas/shilver
Author-email: Jorge Gabín <jorgegabinbrenlla@gmail.com>, Brais Muñiz <mc.brais@gmail.com>
Maintainer-email: Jorge Gabín <jorgegabinbrenlla@gmail.com>, Brais Muñiz <mc.brais@gmail.com>
License-File: LICENSE
Keywords: answer set programming,puzzles,shingoki
Classifier: License :: OSI Approved :: MIT License
Classifier: Operating System :: OS Independent
Classifier: Programming Language :: Python :: 3
Requires-Python: >=3.9
Requires-Dist: clingo
Requires-Dist: clingraph
